<?xml version="1.0" encoding="utf-8"?>
<eml:eml xmlns:eml="eml://ecoinformatics.org/eml-2.1.1" xmlns:xsi="http://www.w3.org/2001/XMLSchema-instance"
         xsi:schemaLocation="eml://ecoinformatics.org/eml-2.1.1 http://rs.gbif.org/schema/eml-gbif-profile/1.2/eml.xsd"
packageId="4208d97a-89c6-47a7-82d8-ac67aee2be44"  system="http://gbif.org" scope="system"
xml:lang="en">

    <dataset>
            <alternateIdentifier>10.15468/fatj1b</alternateIdentifier>
                <alternateIdentifier>589C067B-C8CA-43A8-BE8A-76642BD13093</alternateIdentifier>
                <alternateIdentifier>52EC3D6600B8CA485105C81B56F066A0</alternateIdentifier>
        <title>Myrmica afghanica (Hymenoptera: Formicidae), a new ant species from Afghanistan.</title>
            <creator>
            <individualName>
<givenName>A. G.</givenName>                    <surName>Radchenko</surName>
            </individualName>
            </creator>
            <creator>
            <individualName>
<givenName>G. W.</givenName>                    <surName>Elmes</surName>
            </individualName>
            </creator>
            <metadataProvider>
            <individualName>
<givenName>Thomas</givenName>                    <surName>Stierhof</surName>
            </individualName>
<organizationName>Plazi</organizationName>            </metadataProvider>
            <associatedParty>
<organizationName>Magnolia Press</organizationName>            <address>
<deliveryPoint>St. Lukes 1346</deliveryPoint><city>Auckland</city><country>NEW_ZEALAND</country>            </address>
<electronicMailAddress>magnolia@mapress.com</electronicMailAddress><onlineUrl>http://www.mapress.com/</onlineUrl>            <role>PUBLISHER</role>
            </associatedParty>
            <associatedParty>
<organizationName>Plazi</organizationName>            <address>
<city>Bern</city><country>SWITZERLAND</country>            </address>
<electronicMailAddress>info@plazi.org</electronicMailAddress><onlineUrl>http://plazi.org/</onlineUrl>            <role>DISTRIBUTOR</role>
            </associatedParty>
            <pubDate>
                2003-12-31
            </pubDate>
        <language>ENGLISH</language>
            <abstract>
                    <para>This dataset contains the digitized treatments in Plazi based on the original journal article Radchenko, A. G., Elmes, G. W. (2003): Myrmica afghanica (Hymenoptera: Formicidae), a new ant species from Afghanistan. Zootaxa 375: 1-8, URL: http://atbi.biosci.ohio-state.edu/HymOnline/reference-full.html?id&amp;#61;20235</para>
            </abstract>
            <intellectualRights>
                    <para>To the extent possible under law, the publisher has waived all rights to these data and has dedicated them to the <ulink url="http://creativecommons.org/publicdomain/zero/1.0/legalcode"><citetitle>Public Domain (CC0 1.0)</citetitle></ulink>. Users may copy, modify, distribute and use the work, including for commercial purposes, without restriction.</para>
            </intellectualRights>
            <distribution scope="document">
                <online>
                    <url function="information">http://tb.plazi.org/GgServer/summary/52EC3D6600B8CA485105C81B56F066A0</url>
                </online>
            </distribution>
            <contact>
            <individualName>
<givenName>Guido</givenName>                    <surName>Sautter</surName>
            </individualName>
<electronicMailAddress>gsautter@gmail.com</electronicMailAddress><onlineUrl>http://plazi.org</onlineUrl>            </contact>

    </dataset>

    <additionalMetadata>
        <metadata>
            <gbif>
                <dateStamp>2023-08-28T14:25:31Z</dateStamp>
                <citation>Radchenko A G, Elmes G W, Stierhof T (2003). Myrmica afghanica (Hymenoptera: Formicidae), a new ant species from Afghanistan.. Plazi.org taxonomic treatments database. Checklist dataset https://doi.org/10.15468/fatj1b accessed via GBIF.org on 2023-08-28.</citation>
            </gbif>
        </metadata>
    </additionalMetadata>

</eml:eml>
