<?xml version="1.0" encoding="utf-8"?>
<eml:eml xmlns:eml="eml://ecoinformatics.org/eml-2.1.1" xmlns:xsi="http://www.w3.org/2001/XMLSchema-instance"
         xsi:schemaLocation="eml://ecoinformatics.org/eml-2.1.1 http://rs.gbif.org/schema/eml-gbif-profile/1.2/eml.xsd"
packageId="7f562ba5-17db-46bf-93e8-4d1ba49c2800"  system="http://gbif.org" scope="system"
xml:lang="en">

    <dataset>
            <alternateIdentifier>10.15468/jtu38u</alternateIdentifier>
                <alternateIdentifier>9001B00DFFB75B56FFDAFFF6E270FF89</alternateIdentifier>
        <title>Review of Quedius (Coleoptera, Staphylinidae) described from the 1934 expedition by R. Malaise to Myanmar</title>
            <creator>
            <individualName>
<givenName>Adam James</givenName>                    <surName>Brunke</surName>
            </individualName>
            </creator>
            <metadataProvider>
            <individualName>
                    <surName>felipe</surName>
            </individualName>
<organizationName>Plazi</organizationName>            </metadataProvider>
            <associatedParty>
<organizationName>Plazi</organizationName>            <address>
<city>Bern</city><country>SWITZERLAND</country>            </address>
<electronicMailAddress>info@plazi.org</electronicMailAddress><onlineUrl>https://plazi.org/</onlineUrl>            <role>PUBLISHER</role>
            </associatedParty>
            <pubDate>
                2023-04-20
            </pubDate>
        <language>ENGLISH</language>
            <abstract>
                    <para>This dataset contains the digitized treatments in Plazi based on the original journal article Brunke, Adam James (2023): Review of Quedius (Coleoptera, Staphylinidae) described from the 1934 expedition by R. Malaise to Myanmar. European Journal of Taxonomy 864: 117-145, DOI: https://doi.org/10.5852/ejt.2023.864.2093</para>
            </abstract>
            <intellectualRights>
                    <para>To the extent possible under law, the publisher has waived all rights to these data and has dedicated them to the <ulink url="http://creativecommons.org/publicdomain/zero/1.0/legalcode"><citetitle>Public Domain (CC0 1.0)</citetitle></ulink>. Users may copy, modify, distribute and use the work, including for commercial purposes, without restriction.</para>
            </intellectualRights>
            <distribution scope="document">
                <online>
                    <url function="information">https://tb.plazi.org/GgServer/summary/9001B00DFFB75B56FFDAFFF6E270FF89</url>
                </online>
            </distribution>
            <contact>
            <individualName>
<givenName>Guido</givenName>                    <surName>Sautter</surName>
            </individualName>
<electronicMailAddress>sautter@plazi.org</electronicMailAddress><onlineUrl>https://plazi.org</onlineUrl>            </contact>

    </dataset>

    <additionalMetadata>
        <metadata>
            <gbif>
                <dateStamp>2023-08-28T14:23:08Z</dateStamp>
                <citation>Brunke A J, felipe (2023). Review of Quedius (Coleoptera, Staphylinidae) described from the 1934 expedition by R. Malaise to Myanmar. Plazi.org taxonomic treatments database. Checklist dataset https://doi.org/10.15468/jtu38u accessed via GBIF.org on 2023-08-28.</citation>
                    <bibliography>
                <citation>Brunke, Adam James (2023): Review of Quedius (Coleoptera, Staphylinidae) described from the 1934 expedition by R. Malaise to Myanmar. European Journal of Taxonomy 864: 117-145, DOI: https://doi.org/10.5852/ejt.2023.864.2093</citation>
                    </bibliography>
            </gbif>
        </metadata>
    </additionalMetadata>

</eml:eml>
