<?xml version="1.0" encoding="utf-8"?>
<eml:eml xmlns:eml="eml://ecoinformatics.org/eml-2.1.1" xmlns:xsi="http://www.w3.org/2001/XMLSchema-instance"
         xsi:schemaLocation="eml://ecoinformatics.org/eml-2.1.1 http://rs.gbif.org/schema/eml-gbif-profile/1.2/eml.xsd"
packageId="9cba504a-8bd1-4c19-b911-fea012f6b9ed"  system="http://gbif.org" scope="system"
xml:lang="en">

    <dataset>
            <alternateIdentifier>10.5281/zenodo.4570435</alternateIdentifier>
                <alternateIdentifier>10.15468/cdyfqt</alternateIdentifier>
                <alternateIdentifier>9cba504a-8bd1-4c19-b911-fea012f6b9ed</alternateIdentifier>
                <alternateIdentifier>http://hdl.handle.net/2246/4858</alternateIdentifier>
                <alternateIdentifier>C86BA44E733BFFC9FFCFE814FFD8FFA2</alternateIdentifier>
        <title>Five Newrodents From The Eastern Elburz Moitntains And A New Race Of Hare From Teheran</title>
            <creator>
            <individualName>
<givenName>George G.</givenName>                    <surName>Goodwin</surName>
            </individualName>
            </creator>
            <metadataProvider>
            <individualName>
<givenName>Donat</givenName>                    <surName>Agosti</surName>
            </individualName>
<organizationName>Plazi</organizationName>            </metadataProvider>
            <associatedParty>
<organizationName>Plazi</organizationName>            <address>
<city>Bern</city><country>SWITZERLAND</country>            </address>
<electronicMailAddress>info@plazi.org</electronicMailAddress><onlineUrl>http://plazi.org/</onlineUrl>            <role>PUBLISHER</role>
            </associatedParty>
            <pubDate>
                1939-12-01
            </pubDate>
        <language>ENGLISH</language>
            <abstract>
                    <para>This dataset contains the digitized treatments in Plazi based on the original journal article Goodwin, George G. (1939): Five Newrodents From The Eastern Elburz Moitntains And A New Race Of Hare From Teheran. American Museum Novitates 1050: 1-6, DOI: http://doi.org/10.5281/zenodo.4570435, Hdl: http://hdl.handle.net/2246/4858</para>
            </abstract>
            <intellectualRights>
                    <para>To the extent possible under law, the publisher has waived all rights to these data and has dedicated them to the <ulink url="http://creativecommons.org/publicdomain/zero/1.0/legalcode"><citetitle>Public Domain (CC0 1.0)</citetitle></ulink>. Users may copy, modify, distribute and use the work, including for commercial purposes, without restriction.</para>
            </intellectualRights>
            <distribution scope="document">
                <online>
                    <url function="information">http://tb.plazi.org/GgServer/summary/C86BA44E733BFFC9FFCFE814FFD8FFA2</url>
                </online>
            </distribution>
            <contact>
            <individualName>
<givenName>Guido</givenName>                    <surName>Sautter</surName>
            </individualName>
<electronicMailAddress>gsautter@gmail.com</electronicMailAddress><onlineUrl>http://plazi.org</onlineUrl>            </contact>

    </dataset>

    <additionalMetadata>
        <metadata>
            <gbif>
                <dateStamp>2023-08-28T14:25:08Z</dateStamp>
                <citation>Goodwin G G, Agosti D (1939). Five Newrodents From The Eastern Elburz Moitntains And A New Race Of Hare From Teheran. Plazi.org taxonomic treatments database. Checklist dataset https://doi.org/10.5281/zenodo.4570435 accessed via GBIF.org on 2023-08-28.</citation>
            </gbif>
        </metadata>
    </additionalMetadata>

</eml:eml>
