<?xml version="1.0" encoding="utf-8"?>
<eml:eml xmlns:eml="eml://ecoinformatics.org/eml-2.1.1" xmlns:xsi="http://www.w3.org/2001/XMLSchema-instance"
         xsi:schemaLocation="eml://ecoinformatics.org/eml-2.1.1 http://rs.gbif.org/schema/eml-gbif-profile/1.2/eml.xsd"
packageId="b6794bbb-d7ad-4b53-91ce-e089cf528fda"  system="http://gbif.org" scope="system"
xml:lang="en">

    <dataset>
            <alternateIdentifier>10.11606/1807-0205/2020.60.special-issue.08</alternateIdentifier>
                <alternateIdentifier>b6794bbb-d7ad-4b53-91ce-e089cf528fda</alternateIdentifier>
                <alternateIdentifier>10.15468/3h6tcw</alternateIdentifier>
                <alternateIdentifier>EB32FFFDFFEA6151F70FF350F87BC861</alternateIdentifier>
        <title>Description of the larva and pupa of Apion brevicorne Gerstaecker, 1854 (Coleoptera: Brentidae: Apioninae) with biological information</title>
            <creator>
            <individualName>
<givenName>Rosana Maria de</givenName>                    <surName>Lima</surName>
            </individualName>
            </creator>
            <creator>
            <individualName>
<givenName>Sandreli Berenice de Oliveira</givenName>                    <surName>Santos</surName>
            </individualName>
            </creator>
            <creator>
            <individualName>
<givenName>Stephanie</givenName>                    <surName>Vaz</surName>
            </individualName>
            </creator>
            <creator>
            <individualName>
<givenName>Ana Laura Soares</givenName>                    <surName>Gomes</surName>
            </individualName>
            </creator>
            <creator>
            <individualName>
<givenName>Wesley Oliveira de</givenName>                    <surName>Sousa</surName>
            </individualName>
            </creator>
            <metadataProvider>
            <individualName>
                    <surName>carolina</surName>
            </individualName>
<organizationName>Plazi</organizationName>            </metadataProvider>
            <associatedParty>
<organizationName>Pensoft Publishers</organizationName>            <address>
<deliveryPoint>Prof. Georgi Zlatarski Street 12</deliveryPoint><city>Sofia</city><postalCode>1700</postalCode><country>BULGARIA</country>            </address>
<electronicMailAddress>info@pensoft.net</electronicMailAddress><onlineUrl>http://www.pensoft.net</onlineUrl>            <role>PUBLISHER</role>
            </associatedParty>
            <associatedParty>
<organizationName>Plazi</organizationName>            <address>
<city>Bern</city><country>SWITZERLAND</country>            </address>
<electronicMailAddress>info@plazi.org</electronicMailAddress><onlineUrl>http://plazi.org/</onlineUrl>            <role>DISTRIBUTOR</role>
            </associatedParty>
            <pubDate>
                2020-03-04
            </pubDate>
        <language>ENGLISH</language>
            <abstract>
                    <para>This dataset contains the digitized treatments in Plazi based on the original journal article Lima, Rosana Maria de, Santos, Sandreli Berenice de Oliveira, Vaz, Stephanie, Gomes, Ana Laura Soares, Sousa, Wesley Oliveira de (2020): Description of the larva and pupa of Apion brevicorne Gerstaecker, 1854 (Coleoptera: Brentidae: Apioninae) with biological information. Papéis Avulsos de Zoologia 60 (8): 1-13, DOI: 10.11606/1807-0205/2020.60.special-issue.08</para>
            </abstract>
            <intellectualRights>
                    <para>To the extent possible under law, the publisher has waived all rights to these data and has dedicated them to the <ulink url="http://creativecommons.org/publicdomain/zero/1.0/legalcode"><citetitle>Public Domain (CC0 1.0)</citetitle></ulink>. Users may copy, modify, distribute and use the work, including for commercial purposes, without restriction.</para>
            </intellectualRights>
            <distribution scope="document">
                <online>
                    <url function="information">http://tb.plazi.org/GgServer/summary/EB32FFFDFFEA6151F70FF350F87BC861</url>
                </online>
            </distribution>
            <contact>
            <individualName>
<givenName>Guido</givenName>                    <surName>Sautter</surName>
            </individualName>
<electronicMailAddress>gsautter@gmail.com</electronicMailAddress><onlineUrl>http://plazi.org</onlineUrl>            </contact>

    </dataset>

    <additionalMetadata>
        <metadata>
            <gbif>
                <dateStamp>2023-08-28T14:22:14Z</dateStamp>
                <citation>Lima R M D, Santos S B D O, Vaz S, Gomes A L S, Sousa W O D, carolina (2020). Description of the larva and pupa of Apion brevicorne Gerstaecker, 1854 (Coleoptera: Brentidae: Apioninae) with biological information. Plazi.org taxonomic treatments database. Checklist dataset https://doi.org/10.11606/1807-0205/2020.60.special-issue.08 accessed via GBIF.org on 2023-08-28.</citation>
            </gbif>
        </metadata>
    </additionalMetadata>

</eml:eml>
