<?xml version="1.0" encoding="utf-8"?>
<eml:eml xmlns:eml="eml://ecoinformatics.org/eml-2.1.1" xmlns:xsi="http://www.w3.org/2001/XMLSchema-instance"
         xsi:schemaLocation="eml://ecoinformatics.org/eml-2.1.1 http://rs.gbif.org/schema/eml-gbif-profile/1.2/eml.xsd"
packageId="bce78d34-6879-45e7-b47d-20474a0437f5"  system="http://gbif.org" scope="system"
xml:lang="en">

    <dataset>
            <alternateIdentifier>10.11646/zootaxa.4158.2.4</alternateIdentifier>
                <alternateIdentifier>bce78d34-6879-45e7-b47d-20474a0437f5</alternateIdentifier>
                <alternateIdentifier>10.15468/pm3y4x</alternateIdentifier>
                <alternateIdentifier>70176657-7A08-4036-BFB1-88E235E62DB6</alternateIdentifier>
                <alternateIdentifier>FFCAFC70015D7A07FF870B2A845DFF92</alternateIdentifier>
        <title>Thylacosceles Meyrick new to China, with descriptions of four new species (Lepidoptera: Stathmopodidae)</title>
            <creator>
            <individualName>
<givenName>Wei</givenName>                    <surName>Guan</surName>
            </individualName>
            </creator>
            <creator>
            <individualName>
<givenName>Houhun</givenName>                    <surName>Li</surName>
            </individualName>
            </creator>
            <metadataProvider>
            <individualName>
                    <surName>plazi</surName>
            </individualName>
<organizationName>Plazi</organizationName>            </metadataProvider>
            <associatedParty>
<organizationName>Magnolia Press</organizationName>            <address>
<deliveryPoint>St. Lukes 1346</deliveryPoint><city>Auckland</city><country>NEW_ZEALAND</country>            </address>
<electronicMailAddress>magnolia@mapress.com</electronicMailAddress><onlineUrl>http://www.mapress.com/</onlineUrl>            <role>PUBLISHER</role>
            </associatedParty>
            <associatedParty>
<organizationName>Plazi</organizationName>            <address>
<city>Bern</city><country>SWITZERLAND</country>            </address>
<electronicMailAddress>info@plazi.org</electronicMailAddress><onlineUrl>http://plazi.org/</onlineUrl>            <role>DISTRIBUTOR</role>
            </associatedParty>
            <pubDate>
                2016-12-31
            </pubDate>
        <language>ENGLISH</language>
            <abstract>
                    <para>This dataset contains the digitized treatments in Plazi based on the original journal article Guan, Wei, Li, Houhun (2016): Thylacosceles Meyrick new to China, with descriptions of four new species (Lepidoptera: Stathmopodidae). Zootaxa 4158 (2): 213-220, DOI: http://doi.org/10.11646/zootaxa.4158.2.4</para>
            </abstract>
            <intellectualRights>
                    <para>To the extent possible under law, the publisher has waived all rights to these data and has dedicated them to the <ulink url="http://creativecommons.org/publicdomain/zero/1.0/legalcode"><citetitle>Public Domain (CC0 1.0)</citetitle></ulink>. Users may copy, modify, distribute and use the work, including for commercial purposes, without restriction.</para>
            </intellectualRights>
            <distribution scope="document">
                <online>
                    <url function="information">http://tb.plazi.org/GgServer/summary/FFCAFC70015D7A07FF870B2A845DFF92</url>
                </online>
            </distribution>
            <contact>
            <individualName>
<givenName>Guido</givenName>                    <surName>Sautter</surName>
            </individualName>
<electronicMailAddress>gsautter@gmail.com</electronicMailAddress><onlineUrl>http://plazi.org</onlineUrl>            </contact>

    </dataset>

    <additionalMetadata>
        <metadata>
            <gbif>
                <dateStamp>2023-08-28T14:26:54Z</dateStamp>
                <citation>Guan W, Li H, plazi (2016). Thylacosceles Meyrick new to China, with descriptions of four new species (Lepidoptera: Stathmopodidae). Plazi.org taxonomic treatments database. Checklist dataset https://doi.org/10.11646/zootaxa.4158.2.4 accessed via GBIF.org on 2023-08-28.</citation>
            </gbif>
        </metadata>
    </additionalMetadata>

</eml:eml>
