<?xml version="1.0" encoding="utf-8"?>
<eml:eml xmlns:eml="eml://ecoinformatics.org/eml-2.1.1" xmlns:xsi="http://www.w3.org/2001/XMLSchema-instance"
         xsi:schemaLocation="eml://ecoinformatics.org/eml-2.1.1 http://rs.gbif.org/schema/eml-gbif-profile/1.2/eml.xsd"
packageId="f614d115-44b1-41ef-89ce-8651629bceb0"  system="http://gbif.org" scope="system"
xml:lang="en">

    <dataset>
            <alternateIdentifier>10.15468/44ba75</alternateIdentifier>
                <alternateIdentifier>4E0188A4D3D7563C980CB7C5B9424F3C</alternateIdentifier>
        <title>Lanternfish otoliths (Myctophidae, Teleostei) from the Miocene of Japan</title>
            <creator>
            <individualName>
<givenName>Werner</givenName>                    <surName>Schwarzhans</surName>
            </individualName>
            </creator>
            <creator>
            <individualName>
<givenName>Fumio</givenName>                    <surName>Ohe</surName>
            </individualName>
            </creator>
            <creator>
            <individualName>
<givenName>Yuki</givenName>                    <surName>Tsuchiya</surName>
            </individualName>
            </creator>
            <creator>
            <individualName>
<givenName>Atsushi</givenName>                    <surName>Ujihara</surName>
            </individualName>
            </creator>
            <metadataProvider>
            <individualName>
                    <surName>pensoft</surName>
            </individualName>
<organizationName>Plazi</organizationName>            </metadataProvider>
            <associatedParty>
<organizationName>Pensoft Publishers</organizationName>            <address>
<deliveryPoint>Prof. Georgi Zlatarski Street 12</deliveryPoint><city>Sofia</city><postalCode>1700</postalCode><country>BULGARIA</country>            </address>
<electronicMailAddress>info@pensoft.net</electronicMailAddress><onlineUrl>http://www.pensoft.net</onlineUrl>            <role>PUBLISHER</role>
            </associatedParty>
            <associatedParty>
<organizationName>Plazi</organizationName>            <address>
<city>Bern</city><country>SWITZERLAND</country>            </address>
<electronicMailAddress>info@plazi.org</electronicMailAddress><onlineUrl>http://plazi.org/</onlineUrl>            <role>DISTRIBUTOR</role>
            </associatedParty>
            <pubDate>
                2022-06-10
            </pubDate>
        <language>ENGLISH</language>
            <abstract>
                    <para>This dataset contains the digitized treatments in Plazi based on the original journal article Schwarzhans, Werner, Ohe, Fumio, Tsuchiya, Yuki, Ujihara, Atsushi (2022): Lanternfish otoliths (Myctophidae, Teleostei) from the Miocene of Japan. Zitteliana 96: 103-134, DOI: http://dx.doi.org/10.3897/zitteliana.96.83571, URL: http://dx.doi.org/10.3897/zitteliana.96.83571</para>
            </abstract>
            <intellectualRights>
                    <para>To the extent possible under law, the publisher has waived all rights to these data and has dedicated them to the <ulink url="http://creativecommons.org/publicdomain/zero/1.0/legalcode"><citetitle>Public Domain (CC0 1.0)</citetitle></ulink>. Users may copy, modify, distribute and use the work, including for commercial purposes, without restriction.</para>
            </intellectualRights>
            <distribution scope="document">
                <online>
                    <url function="information">http://tb.plazi.org/GgServer/summary/4E0188A4D3D7563C980CB7C5B9424F3C</url>
                </online>
            </distribution>
            <contact>
            <individualName>
<givenName>Guido</givenName>                    <surName>Sautter</surName>
            </individualName>
<electronicMailAddress>gsautter@gmail.com</electronicMailAddress><onlineUrl>http://plazi.org</onlineUrl>            </contact>

    </dataset>

    <additionalMetadata>
        <metadata>
            <gbif>
                <dateStamp>2023-08-28T14:12:36Z</dateStamp>
                <citation>Schwarzhans W, Ohe F, Tsuchiya Y, Ujihara A, pensoft (2022). Lanternfish otoliths (Myctophidae, Teleostei) from the Miocene of Japan. Plazi.org taxonomic treatments database. Checklist dataset https://doi.org/10.15468/44ba75 accessed via GBIF.org on 2023-08-28.</citation>
            </gbif>
        </metadata>
    </additionalMetadata>

</eml:eml>
