<?xml version="1.0" encoding="utf-8"?>
<eml:eml xmlns:eml="eml://ecoinformatics.org/eml-2.1.1" xmlns:xsi="http://www.w3.org/2001/XMLSchema-instance"
         xsi:schemaLocation="eml://ecoinformatics.org/eml-2.1.1 http://rs.gbif.org/schema/eml-gbif-profile/1.2/eml.xsd"
packageId="f9645963-d85a-49a5-b067-4dd7860c4ebf"  system="http://gbif.org" scope="system"
xml:lang="en">

    <dataset>
            <alternateIdentifier>10.15468/zyjptk</alternateIdentifier>
                <alternateIdentifier>FF83A75A9331FFFBFFB5361AFFA45B3F</alternateIdentifier>
        <title>Revision of Heteroscelis Latreille, 1829 (Heteroptera: Pentatomidae: Asopinae) with the description of a new species from Colombia</title>
            <creator>
            <individualName>
<givenName>Vinicius Gomes</givenName>                    <surName>Sampaio</surName>
            </individualName>
            </creator>
            <creator>
            <individualName>
<givenName>Talita</givenName>                    <surName>Roell</surName>
            </individualName>
            </creator>
            <creator>
            <individualName>
<givenName>Luiz Alexandre</givenName>                    <surName>Campos</surName>
            </individualName>
            </creator>
            <metadataProvider>
            <individualName>
                    <surName>plazi</surName>
            </individualName>
<organizationName>Plazi</organizationName>            </metadataProvider>
            <associatedParty>
<organizationName>Magnolia Press</organizationName>            <address>
<deliveryPoint>St. Lukes 1346</deliveryPoint><city>Auckland</city><country>NEW_ZEALAND</country>            </address>
<electronicMailAddress>magnolia@mapress.com</electronicMailAddress><onlineUrl>https://www.mapress.com/</onlineUrl>            <role>PUBLISHER</role>
            </associatedParty>
            <associatedParty>
<organizationName>Plazi</organizationName>            <address>
<city>Bern</city><country>SWITZERLAND</country>            </address>
<electronicMailAddress>info@plazi.org</electronicMailAddress><onlineUrl>https://plazi.org/</onlineUrl>            <role>DISTRIBUTOR</role>
            </associatedParty>
            <pubDate>
                2023-05-08
            </pubDate>
        <language>ENGLISH</language>
            <abstract>
                    <para>This dataset contains the digitized treatments in Plazi based on the original journal article Sampaio, Vinicius Gomes, Roell, Talita, Campos, Luiz Alexandre (2023): Revision of Heteroscelis Latreille, 1829 (Heteroptera: Pentatomidae: Asopinae) with the description of a new species from Colombia. Zootaxa 5278 (3): 401-438, DOI: 10.11646/zootaxa.5278.3.1, URL: http://dx.doi.org/10.11646/zootaxa.5278.3.1</para>
            </abstract>
            <intellectualRights>
                    <para>To the extent possible under law, the publisher has waived all rights to these data and has dedicated them to the <ulink url="http://creativecommons.org/publicdomain/zero/1.0/legalcode"><citetitle>Public Domain (CC0 1.0)</citetitle></ulink>. Users may copy, modify, distribute and use the work, including for commercial purposes, without restriction.</para>
            </intellectualRights>
            <distribution scope="document">
                <online>
                    <url function="information">https://tb.plazi.org/GgServer/summary/FF83A75A9331FFFBFFB5361AFFA45B3F</url>
                </online>
            </distribution>
            <contact>
            <individualName>
<givenName>Guido</givenName>                    <surName>Sautter</surName>
            </individualName>
<electronicMailAddress>sautter@plazi.org</electronicMailAddress><onlineUrl>https://plazi.org</onlineUrl>            </contact>

    </dataset>

    <additionalMetadata>
        <metadata>
            <gbif>
                <dateStamp>2023-08-28T14:12:56Z</dateStamp>
                <citation>Sampaio V G, Roell T, Campos L A, plazi (2023). Revision of Heteroscelis Latreille, 1829 (Heteroptera: Pentatomidae: Asopinae) with the description of a new species from Colombia. Plazi.org taxonomic treatments database. Checklist dataset https://doi.org/10.15468/zyjptk accessed via GBIF.org on 2023-08-28.</citation>
                    <bibliography>
                <citation>Sampaio, Vinicius Gomes, Roell, Talita, Campos, Luiz Alexandre (2023): Revision of Heteroscelis Latreille, 1829 (Heteroptera: Pentatomidae: Asopinae) with the description of a new species from Colombia. Zootaxa 5278 (3): 401-438, DOI: 10.11646/zootaxa.5278.3.1, URL: http://dx.doi.org/10.11646/zootaxa.5278.3.1</citation>
                    </bibliography>
            </gbif>
        </metadata>
    </additionalMetadata>

</eml:eml>
