<?xml version="1.0" encoding="utf-8"?>
<eml:eml xmlns:eml="eml://ecoinformatics.org/eml-2.1.1" xmlns:xsi="http://www.w3.org/2001/XMLSchema-instance"
         xsi:schemaLocation="eml://ecoinformatics.org/eml-2.1.1 http://rs.gbif.org/schema/eml-gbif-profile/1.2/eml.xsd"
packageId="fc23db36-464b-42fb-b4dc-95d6df92600b"  system="http://gbif.org" scope="system"
xml:lang="en">

    <dataset>
            <alternateIdentifier>10.3897/zookeys.39.438</alternateIdentifier>
                <alternateIdentifier>fc23db36-464b-42fb-b4dc-95d6df92600b</alternateIdentifier>
                <alternateIdentifier>10.15468/7ckrcc</alternateIdentifier>
                <alternateIdentifier>6AF950B9-F8A5-4FF1-8F6A-BFF4FD8F79DE</alternateIdentifier>
                <alternateIdentifier>FF94711ABB2DC84A7D44FFF82B72CE7D</alternateIdentifier>
        <title>A revision of the genus Hypotrix Guenee in North America with descriptions of four new species and a new genus (Lepidoptera, Noctuidae, Noctuinae, Eriopygini)</title>
            <creator>
            <individualName>
<givenName>Donald</givenName>                    <surName>Lafontaine</surName>
            </individualName>
            </creator>
            <creator>
            <individualName>
<givenName>Clifford</givenName>                    <surName>Ferris</surName>
            </individualName>
            </creator>
            <creator>
            <individualName>
<givenName>J.</givenName>                    <surName>Walsh</surName>
            </individualName>
            </creator>
            <metadataProvider>
            <individualName>
                    <surName>plazi</surName>
            </individualName>
<organizationName>Plazi</organizationName>            </metadataProvider>
            <associatedParty>
<organizationName>Pensoft Publishers</organizationName>            <address>
<deliveryPoint>Prof. Georgi Zlatarski Street 12</deliveryPoint><city>Sofia</city><postalCode>1700</postalCode><country>BULGARIA</country>            </address>
<electronicMailAddress>info@pensoft.net</electronicMailAddress><onlineUrl>http://www.pensoft.net</onlineUrl>            <role>PUBLISHER</role>
            </associatedParty>
            <associatedParty>
<organizationName>Plazi</organizationName>            <address>
<city>Bern</city><country>SWITZERLAND</country>            </address>
<electronicMailAddress>info@plazi.org</electronicMailAddress><onlineUrl>http://plazi.org/</onlineUrl>            <role>DISTRIBUTOR</role>
            </associatedParty>
            <pubDate>
                2010-03-18
            </pubDate>
        <language>ENGLISH</language>
            <abstract>
                    <para>This dataset contains the digitized treatments in Plazi based on the original journal article Lafontaine, Donald, Ferris, Clifford, Walsh, J. (2010): A revision of the genus Hypotrix Guenee in North America with descriptions of four new species and a new genus (Lepidoptera, Noctuidae, Noctuinae, Eriopygini). ZooKeys 39 (39): 225-253, DOI: 10.3897/zookeys.39.438</para>
            </abstract>
            <intellectualRights>
                    <para>To the extent possible under law, the publisher has waived all rights to these data and has dedicated them to the <ulink url="http://creativecommons.org/publicdomain/zero/1.0/legalcode"><citetitle>Public Domain (CC0 1.0)</citetitle></ulink>. Users may copy, modify, distribute and use the work, including for commercial purposes, without restriction.</para>
            </intellectualRights>
            <distribution scope="document">
                <online>
                    <url function="information">http://tb.plazi.org/GgServer/summary/FF94711ABB2DC84A7D44FFF82B72CE7D</url>
                </online>
            </distribution>
            <contact>
            <individualName>
<givenName>Guido</givenName>                    <surName>Sautter</surName>
            </individualName>
<electronicMailAddress>gsautter@gmail.com</electronicMailAddress><onlineUrl>http://plazi.org</onlineUrl>            </contact>

    </dataset>

    <additionalMetadata>
        <metadata>
            <gbif>
                <dateStamp>2023-08-28T14:19:52Z</dateStamp>
                <citation>Lafontaine D, Ferris C, Walsh J, plazi (2010). A revision of the genus Hypotrix Guenee in North America with descriptions of four new species and a new genus (Lepidoptera, Noctuidae, Noctuinae, Eriopygini). Plazi.org taxonomic treatments database. Checklist dataset https://doi.org/10.3897/zookeys.39.438 accessed via GBIF.org on 2023-08-28.</citation>
            </gbif>
        </metadata>
    </additionalMetadata>

</eml:eml>
